scryptopy/__init__.py
scryptopy/scrypto.py
scryptopy-0.12.1.dist-info/LICENSE
scryptopy-0.12.1.dist-info/METADATA
scryptopy-0.12.1.dist-info/WHEEL
scryptopy-0.12.1.dist-info/entry_points.txt
scryptopy-0.12.1.dist-info/top_level.txt
scryptopy-0.12.1.dist-info/RECORD
