Metadata-Version: 2.1
Name: scryptopy
Version: 0.12.1
Summary: a Python library for salty encryption and decryption of files and directories
Home-page: https://github.com/kdrobnyh/scryptopy
Author: Klim Drobnyh
Author-email: klim.drobnyh@gmail.com
License: GNU General Public License v3 (GPLv3)
Project-URL: Source, https://github.com/kdrobnyh/scryptopy
Project-URL: Tracker, https://github.com/kdrobnyh/scryptopy/issues
Classifier: Development Status :: 4 - Beta
Classifier: Environment :: Console
Classifier: Intended Audience :: End Users/Desktop
Classifier: License :: OSI Approved :: GNU General Public License v3 or later (GPLv3+)
Classifier: Natural Language :: English
Classifier: Operating System :: POSIX :: Linux
Classifier: Programming Language :: Python :: 3.7
Classifier: Programming Language :: Python :: 3.8
Classifier: Programming Language :: Python :: 3.9
Classifier: Programming Language :: Python :: 3.10
Classifier: Topic :: Security :: Cryptography
Requires-Python: >=3.7
License-File: LICENSE
Requires-Dist: python-gnupg (>=0.4.6)
Requires-Dist: jsonschema (>=3.2.0)
Requires-Dist: click (>=8.0.0)
